optimum/commands/export/executorch.py
optimum/commands/register/register_export.py
optimum/executorch/__init__.py
optimum/executorch/modeling.py
optimum/executorch/stats.py
optimum/executorch/version.py
optimum/executorch/attentions/custom_kv_cache.py
optimum/executorch/attentions/custom_sdpa.py
optimum/executorch/passes/remove_padding_idx_embedding_pass.py
optimum/exporters/executorch/__init__.py
optimum/exporters/executorch/__main__.py
optimum/exporters/executorch/convert.py
optimum/exporters/executorch/integrations.py
optimum/exporters/executorch/quantization.py
optimum/exporters/executorch/recipe_registry.py
optimum/exporters/executorch/task_registry.py
optimum/exporters/executorch/utils.py
optimum/exporters/executorch/recipes/__init__.py
optimum/exporters/executorch/recipes/coreml.py
optimum/exporters/executorch/recipes/cuda.py
optimum/exporters/executorch/recipes/metal.py
optimum/exporters/executorch/recipes/portable.py
optimum/exporters/executorch/recipes/xnnpack.py
optimum/exporters/executorch/tasks/__init__.py
optimum/exporters/executorch/tasks/asr.py
optimum/exporters/executorch/tasks/causal_lm.py
optimum/exporters/executorch/tasks/image_classification.py
optimum/exporters/executorch/tasks/masked_lm.py
optimum/exporters/executorch/tasks/multimodal_text_to_text.py
optimum/exporters/executorch/tasks/seq2seq_lm.py
optimum_executorch-0.1.0.dist-info/licenses/LICENSE
optimum_executorch-0.1.0.dist-info/METADATA
optimum_executorch-0.1.0.dist-info/WHEEL
optimum_executorch-0.1.0.dist-info/top_level.txt
optimum_executorch-0.1.0.dist-info/RECORD
