Metadata-Version: 2.4
Name: optimum-executorch
Version: 0.1.0
Summary: Optimum Executorch is an interface between the Hugging Face libraries and ExecuTorch
Author-email: "HuggingFace Inc. Special Ops Team" <hardware@huggingface.co>
License: Apache
Project-URL: Homepage, https://github.com/huggingface/optimum-executorch
Keywords: transformers,quantization,inference,executorch
Classifier: Development Status :: 2 - Pre-Alpha
Classifier: License :: OSI Approved :: Apache Software License
Classifier: Intended Audience :: Developers
Classifier: Intended Audience :: Education
Classifier: Intended Audience :: Science/Research
Classifier: Operating System :: OS Independent
Classifier: Programming Language :: Python :: 3
Classifier: Programming Language :: Python :: 3.10
Classifier: Programming Language :: Python :: 3.11
Classifier: Programming Language :: Python :: 3.12
Classifier: Topic :: Scientific/Engineering :: Artificial Intelligence
Requires-Python: >=3.10.0
License-File: LICENSE
Requires-Dist: optimum~=1.24
Requires-Dist: executorch>=1.0.0
Requires-Dist: transformers==4.56.1
Requires-Dist: pytorch-tokenizers>=1.0.1
Requires-Dist: accelerate>=0.26.0
Provides-Extra: dev
Requires-Dist: accelerate>=0.26.0; extra == "dev"
Requires-Dist: coremltools>=8.2.0; extra == "dev"
Requires-Dist: datasets==3.6.0; extra == "dev"
Requires-Dist: parameterized; extra == "dev"
Requires-Dist: pytest; extra == "dev"
Requires-Dist: safetensors; extra == "dev"
Requires-Dist: sentencepiece; extra == "dev"
Requires-Dist: numba!=0.58.0; extra == "dev"
Requires-Dist: librosa; extra == "dev"
Requires-Dist: soundfile; extra == "dev"
Requires-Dist: tiktoken; extra == "dev"
Requires-Dist: black~=23.1; extra == "dev"
Requires-Dist: ruff==0.4.4; extra == "dev"
Dynamic: license-file
